treat_like/__init__.py
treat_like/converters.py
treat_like/exceptions.py
treat_like/form.py
treat_like/template.py
treat_like/treat.py
treat_like/treat_results.py
treat_like/validators.py
treat_like-0.11.dist-info/METADATA
treat_like-0.11.dist-info/WHEEL
treat_like-0.11.dist-info/top_level.txt
treat_like-0.11.dist-info/RECORD
