Metadata-Version: 2.1
Name: treat-like
Version: 0.11
Summary: Python library for processing and validation user input data
Home-page: https://github.com/atomAltera/treat_like
Author: Konstantin Alikhanov
Author-email: atomAltera@gmail.com
License: MIT
Platform: UNKNOWN
